{
  "action": "created",
  "discussion": {
    "active_lock_reason": null,
    "answer_chosen_at": null,
    "answer_chosen_by": null,
    "answer_html_url": null,
    "author_association": "OWNER",
    "body": "What is github pages",
    "category": {
      "created_at": "2023-08-23T15:54:26.000+05:30",
      "description": "Chat about anything and everything here",
      "emoji": ":speech_balloon:",
      "id": 40055731,
      "is_answerable": false,
      "name": "General",
      "node_id": "DIC_kwDOKKceBM4CYzOz",
      "repository_id": 682040836,
      "slug": "general",
      "updated_at": "2023-08-23T15:54:26.000+05:30"
    },
    "comments": 0,
    "created_at": "2023-08-23T13:32:08Z",
    "html_url": "https://github.com/kiran-godse/discussion-generator/discussions/15",
    "id": 5550638,
    "locked": false,
    "node_id": "D_kwDOKKceBM4AVLIu",
    "number": 15,
    "reactions": {
      "+1": 0,
      "-1": 0,
      "confused": 0,
      "eyes": 0,
      "heart": 0,
      "hooray": 0,
      "laugh": 0,
      "rocket": 0,
      "total_count": 0,
      "url": "https://api.github.com/repos/kiran-godse/discussion-generator/discussions/15/reactions"
    },
    "repository_url": "https://api.github.com/repos/kiran-godse/discussion-generator",
    "state": "open",
    "state_reason": null,
    "timeline_url": "https://api.github.com/repos/kiran-godse/discussion-generator/discussions/15/timeline",
    "title": "github",
    "updated_at": "2023-08-23T13:32:08Z",
    "user": {
      "avatar_url": "https://avatars.githubusercontent.com/u/82302395?v=4",
      "events_url": "https://api.github.com/users/kiran-godse/events{/privacy}",
      "followers_url": "https://api.github.com/users/kiran-godse/followers",
      "following_url": "https://api.github.com/users/kiran-godse/following{/other_user}",
      "gists_url": "https://api.github.com/users/kiran-godse/gists{/gist_id}",
      "gravatar_id": "",
      "html_url": "https://github.com/kiran-godse",
      "id": 82302395,
      "login": "kiran-godse",
      "node_id": "MDQ6VXNlcjgyMzAyMzk1",
      "organizations_url": "https://api.github.com/users/kiran-godse/orgs",
      "received_events_url": "https://api.github.com/users/kiran-godse/received_events",
      "repos_url": "https://api.github.com/users/kiran-godse/repos",
      "site_admin": false,
      "starred_url": "https://api.github.com/users/kiran-godse/starred{/owner}{/repo}",
      "subscriptions_url": "https://api.github.com/users/kiran-godse/subscriptions",
      "type": "User",
      "url": "https://api.github.com/users/kiran-godse"
    }
  },
  "repository": {
    "allow_forking": true,
    "archive_url": "https://api.github.com/repos/kiran-godse/discussion-generator/{archive_format}{/ref}",
    "archived": false,
    "assignees_url": "https://api.github.com/repos/kiran-godse/discussion-generator/assignees{/user}",
    "blobs_url": "https://api.github.com/repos/kiran-godse/discussion-generator/git/blobs{/sha}",
    "branches_url": "https://api.github.com/repos/kiran-godse/discussion-generator/branches{/branch}",
    "clone_url": "https://github.com/kiran-godse/discussion-generator.git",
    "collaborators_url": "https://api.github.com/repos/kiran-godse/discussion-generator/collaborators{/collaborator}",
    "comments_url": "https://api.github.com/repos/kiran-godse/discussion-generator/comments{/number}",
    "commits_url": "https://api.github.com/repos/kiran-godse/discussion-generator/commits{/sha}",
    "compare_url": "https://api.github.com/repos/kiran-godse/discussion-generator/compare/{base}...{head}",
    "contents_url": "https://api.github.com/repos/kiran-godse/discussion-generator/contents/{+path}",
    "contributors_url": "https://api.github.com/repos/kiran-godse/discussion-generator/contributors",
    "created_at": "2023-08-23T10:03:47Z",
    "default_branch": "main",
    "deployments_url": "https://api.github.com/repos/kiran-godse/discussion-generator/deployments",
    "description": null,
    "disabled": false,
    "downloads_url": "https://api.github.com/repos/kiran-godse/discussion-generator/downloads",
    "events_url": "https://api.github.com/repos/kiran-godse/discussion-generator/events",
    "fork": false,
    "forks": 0,
    "forks_count": 0,
    "forks_url": "https://api.github.com/repos/kiran-godse/discussion-generator/forks",
    "full_name": "kiran-godse/discussion-generator",
    "git_commits_url": "https://api.github.com/repos/kiran-godse/discussion-generator/git/commits{/sha}",
    "git_refs_url": "https://api.github.com/repos/kiran-godse/discussion-generator/git/refs{/sha}",
    "git_tags_url": "https://api.github.com/repos/kiran-godse/discussion-generator/git/tags{/sha}",
    "git_url": "git://github.com/kiran-godse/discussion-generator.git",
    "has_discussions": true,
    "has_downloads": true,
    "has_issues": true,
    "has_pages": false,
    "has_projects": true,
    "has_wiki": true,
    "homepage": null,
    "hooks_url": "https://api.github.com/repos/kiran-godse/discussion-generator/hooks",
    "html_url": "https://github.com/kiran-godse/discussion-generator",
    "id": 682040836,
    "is_template": false,
    "issue_comment_url": "https://api.github.com/repos/kiran-godse/discussion-generator/issues/comments{/number}",
    "issue_events_url": "https://api.github.com/repos/kiran-godse/discussion-generator/issues/events{/number}",
    "issues_url": "https://api.github.com/repos/kiran-godse/discussion-generator/issues{/number}",
    "keys_url": "https://api.github.com/repos/kiran-godse/discussion-generator/keys{/key_id}",
    "labels_url": "https://api.github.com/repos/kiran-godse/discussion-generator/labels{/name}",
    "language": "JavaScript",
    "languages_url": "https://api.github.com/repos/kiran-godse/discussion-generator/languages",
    "license": null,
    "merges_url": "https://api.github.com/repos/kiran-godse/discussion-generator/merges",
    "milestones_url": "https://api.github.com/repos/kiran-godse/discussion-generator/milestones{/number}",
    "mirror_url": null,
    "name": "discussion-generator",
    "node_id": "R_kgDOKKceBA",
    "notifications_url": "https://api.github.com/repos/kiran-godse/discussion-generator/notifications{?since,all,participating}",
    "open_issues": 0,
    "open_issues_count": 0,
    "owner": {
      "avatar_url": "https://avatars.githubusercontent.com/u/82302395?v=4",
      "events_url": "https://api.github.com/users/kiran-godse/events{/privacy}",
      "followers_url": "https://api.github.com/users/kiran-godse/followers",
      "following_url": "https://api.github.com/users/kiran-godse/following{/other_user}",
      "gists_url": "https://api.github.com/users/kiran-godse/gists{/gist_id}",
      "gravatar_id": "",
      "html_url": "https://github.com/kiran-godse",
      "id": 82302395,
      "login": "kiran-godse",
      "node_id": "MDQ6VXNlcjgyMzAyMzk1",
      "organizations_url": "https://api.github.com/users/kiran-godse/orgs",
      "received_events_url": "https://api.github.com/users/kiran-godse/received_events",
      "repos_url": "https://api.github.com/users/kiran-godse/repos",
      "site_admin": false,
      "starred_url": "https://api.github.com/users/kiran-godse/starred{/owner}{/repo}",
      "subscriptions_url": "https://api.github.com/users/kiran-godse/subscriptions",
      "type": "User",
      "url": "https://api.github.com/users/kiran-godse"
    },
    "private": false,
    "pulls_url": "https://api.github.com/repos/kiran-godse/discussion-generator/pulls{/number}",
    "pushed_at": "2023-08-24T06:23:09Z",
    "releases_url": "https://api.github.com/repos/kiran-godse/discussion-generator/releases{/id}",
    "size": 57,
    "ssh_url": "git@github.com:kiran-godse/discussion-generator.git",
    "stargazers_count": 0,
    "stargazers_url": "https://api.github.com/repos/kiran-godse/discussion-generator/stargazers",
    "statuses_url": "https://api.github.com/repos/kiran-godse/discussion-generator/statuses/{sha}",
    "subscribers_url": "https://api.github.com/repos/kiran-godse/discussion-generator/subscribers",
    "subscription_url": "https://api.github.com/repos/kiran-godse/discussion-generator/subscription",
    "svn_url": "https://github.com/kiran-godse/discussion-generator",
    "tags_url": "https://api.github.com/repos/kiran-godse/discussion-generator/tags",
    "teams_url": "https://api.github.com/repos/kiran-godse/discussion-generator/teams",
    "topics": [],
    "trees_url": "https://api.github.com/repos/kiran-godse/discussion-generator/git/trees{/sha}",
    "updated_at": "2023-08-23T10:04:54Z",
    "url": "https://api.github.com/repos/kiran-godse/discussion-generator",
    "visibility": "public",
    "watchers": 0,
    "watchers_count": 0,
    "web_commit_signoff_required": false
  },
  "sender": {
    "avatar_url": "https://avatars.githubusercontent.com/u/82302395?v=4",
    "events_url": "https://api.github.com/users/kiran-godse/events{/privacy}",
    "followers_url": "https://api.github.com/users/kiran-godse/followers",
    "following_url": "https://api.github.com/users/kiran-godse/following{/other_user}",
    "gists_url": "https://api.github.com/users/kiran-godse/gists{/gist_id}",
    "gravatar_id": "",
    "html_url": "https://github.com/kiran-godse",
    "id": 82302395,
    "login": "kiran-godse",
    "node_id": "MDQ6VXNlcjgyMzAyMzk1",
    "organizations_url": "https://api.github.com/users/kiran-godse/orgs",
    "received_events_url": "https://api.github.com/users/kiran-godse/received_events",
    "repos_url": "https://api.github.com/users/kiran-godse/repos",
    "site_admin": false,
    "starred_url": "https://api.github.com/users/kiran-godse/starred{/owner}{/repo}",
    "subscriptions_url": "https://api.github.com/users/kiran-godse/subscriptions",
    "type": "User",
    "url": "https://api.github.com/users/kiran-godse"
  }
}
